{"no_cuda": true, "accimage": true, "output_topk": 5, "distributed": true, "manual_seed": 1, "dist_url": "tcp://127.0.0.1:23456", "model": "resnet", "n_classes": 3, "n_pretrain_classes": 0, "pretrain_path": null, "model_depth": 101, "conv1_t_size": 7, "conv1_t_stride": 1, "no_max_pool": false, "resnet_shortcut": "B", "resnet_widen_factor": 1.0, "resnext_cardinality": 32, "wide_resnet_k": 2, "batchnorm_sync": true, "root_path": "/home/ram/Workspace/training", "data_path": "/home/ram/Workspace/training/data", "result_path": "/home/ram/Workspace/training/save", "resume_path": "/home/ram/Workspace/training/results", "resume_file": "/home/ram/Workspace/training/results/save_150.pth", "ft_begin_module": "", "no_train": false, "no_val": false, "inference": false, "inference_subset": "val", "inference_stride": 16, "inference_crop": "center", "inference_no_average": false, "sample_size": 112, "train_crop_min_scale": 0.25, "train_crop_min_ratio": 0.75, "no_mean_norm": false, "no_std_norm": false, "no_hflip": false, "colorjitter": false, "input_type": "flow", "value_scale": 1, "nesterov": false, "optimizer": "sgd", "lr_scheduler": "multistep", "multistep_milestones": [50, 100, 150], "overwrite_milestones": false, "plateau_patience": 10, "batch_size": 4, "inference_batch_size": 4, "dampening": 0.0, "weight_decay": 0.001, "learning_rate": 0.1, "momentum": 0.8, "world_size": -1, "n_threads": 8, "n_val_samples": 2, "tensorboard": false, "n_epochs": 300, "checkpoint": 10, "arch": "resnet-101", "begin_epoch": 1, "n_input_channels": 3, "dist_rank": 0}